LICENSE
MANIFEST.in
NOTICE
README.rst
VERSION
setup.cfg
setup.py
src/sagemaker_inference/__init__.py
src/sagemaker_inference/content_types.py
src/sagemaker_inference/decoder.py
src/sagemaker_inference/default_handler_service.py
src/sagemaker_inference/default_inference_handler.py
src/sagemaker_inference/encoder.py
src/sagemaker_inference/environment.py
src/sagemaker_inference/errors.py
src/sagemaker_inference/logging.py
src/sagemaker_inference/model_server.py
src/sagemaker_inference/parameters.py
src/sagemaker_inference/transformer.py
src/sagemaker_inference/utils.py
src/sagemaker_pytorch_inference.egg-info/PKG-INFO
src/sagemaker_pytorch_inference.egg-info/SOURCES.txt
src/sagemaker_pytorch_inference.egg-info/dependency_links.txt
src/sagemaker_pytorch_inference.egg-info/entry_points.txt
src/sagemaker_pytorch_inference.egg-info/requires.txt
src/sagemaker_pytorch_inference.egg-info/top_level.txt
src/sagemaker_pytorch_serving_container/__init__.py
src/sagemaker_pytorch_serving_container/default_pytorch_inference_handler.py
src/sagemaker_pytorch_serving_container/handler_service.py
src/sagemaker_pytorch_serving_container/serving.py
src/sagemaker_pytorch_serving_container/torchserve.py
src/sagemaker_pytorch_serving_container/ts_environment.py
src/sagemaker_pytorch_serving_container/ts_parameters.py
src/sagemaker_pytorch_serving_container/etc/default-ts.properties
src/sagemaker_pytorch_serving_container/etc/log4j2.xml
src/sagemaker_pytorch_serving_container/etc/mme-ts.properties