Metadata-Version: 2.1
Name: sagemaker-pytorch-inference
Version: 2.0.23
Summary: Open source library for creating PyTorch containers to run on Amazon SageMaker.
Home-page: https://github.com/aws/sagemaker-pytorch-inference-toolkit
Author: Amazon Web Services
License: Apache License 2.0
Platform: UNKNOWN
Classifier: Development Status :: 5 - Production/Stable
Classifier: Intended Audience :: Developers
Classifier: Natural Language :: English
Classifier: License :: OSI Approved :: Apache Software License
Classifier: Programming Language :: Python
Classifier: Programming Language :: Python :: 3.8
Classifier: Programming Language :: Python :: 3.9
Classifier: Programming Language :: Python :: 3.10
Provides-Extra: test
